coactive/__init__.py
coactive/client.py
coactive/core/__init__.py
coactive/core/api_error.py
coactive/core/client_wrapper.py
coactive/core/datetime_utils.py
coactive/core/jsonable_encoder.py
coactive/core/remove_none_from_dict.py
coactive/environment.py
coactive/errors/__init__.py
coactive/errors/bad_request_error.py
coactive/errors/forbidden_error.py
coactive/errors/not_found_error.py
coactive/errors/unauthorized_error.py
coactive/errors/unprocessable_entity_error.py
coactive/py.typed
coactive/resources/__init__.py
coactive/resources/classification/__init__.py
coactive/resources/classification/client.py
coactive/resources/concept/__init__.py
coactive/resources/concept/client.py
coactive/resources/credentials/__init__.py
coactive/resources/credentials/client.py
coactive/resources/dataset/__init__.py
coactive/resources/dataset/client.py
coactive/resources/embedding/__init__.py
coactive/resources/embedding/client.py
coactive/resources/image/__init__.py
coactive/resources/image/client.py
coactive/resources/label/__init__.py
coactive/resources/label/client.py
coactive/resources/query/__init__.py
coactive/resources/query/client.py
coactive/resources/similarity_search/__init__.py
coactive/resources/similarity_search/client.py
coactive/types/__init__.py
coactive/types/add_asset_item.py
coactive/types/asset.py
coactive/types/asset_metadata.py
coactive/types/asset_response.py
coactive/types/asset_type.py
coactive/types/audio_segment.py
coactive/types/basic_description.py
coactive/types/candidates_to_label_response.py
coactive/types/classification.py
coactive/types/classification_embedding_vector_request.py
coactive/types/classification_response.py
coactive/types/classification_score.py
coactive/types/column.py
coactive/types/column_data_type.py
coactive/types/column_display_type.py
coactive/types/column_style.py
coactive/types/concept_label_request.py
coactive/types/concept_list_response.py
coactive/types/concept_response.py
coactive/types/credentials.py
fern_coactive-0.1.0.dist-info/METADATA
fern_coactive-0.1.0.dist-info/WHEEL
fern_coactive-0.1.0.dist-info/RECORD
